{"_ts":[1504256763,1504300431,1504344171,1504387838],"_r":{"breakdown":{"html":{"bytes":[23681,23682,23684,23691],"requests":[8,8,8,8]},"js":{"bytes":[555275,555364,555293,555359],"requests":[33,33,33,33]},"css":{"bytes":[75960,75969,75960,75969],"requests":[6,6,6,6]},"image":{"bytes":[175073,175095,175095,174519],"requests":[26,26,26,25]},"flash":{"bytes":[0,0,0,0],"requests":[0,0,0,0]},"font":{"bytes":[198570,198570,198570,198570],"requests":[9,9,9,9]},"other":{"bytes":[11940,11958,11939,11940],"requests":[20,20,20,21]}},"date":[1504256763,1504300431,1504344171,1504387838],"domElements":[1165,1165,1165,1165],"domInteractive":[2669,2135,2084,2148],"firstPaint":[2609,1992,2040,2090],"fullyLoaded":[5797,3833,4054,4305],"id":["170901_B5_8ca5d219ea70a7bef4c31d86b7703a33","170901_BD_b816c0227f11fe28a3a91172b64e98fa","170902_Z9_bf9641142b46865f7233c97ee0c858ba","170902_9B_10eea5fa426fe057a8b8b547de417886"],"loadTime":[5484,3514,3643,3764],"render":[2933,1967,2633,2100],"SpeedIndex":[2940,2236,2639,2381],"TTFB":[906,1088,1031,979],"videoFrames":[[{"_i":"ms_000000.jpg","_t":0,"_vc":0},{"_i":"ms_002933.jpg","_t":2933,"_vc":99},{"_i":"ms_003000.jpg","_t":3000,"_vc":99},{"_i":"ms_003233.jpg","_t":3233,"_vc":99},{"_i":"ms_003500.jpg","_t":3500,"_vc":99},{"_i":"ms_003700.jpg","_t":3700,"_vc":100},{"_i":"ms_003733.jpg","_t":3733,"_vc":100},{"_i":"ms_005800.jpg","_t":5800,"_vc":100},{"_i":"ms_005833.jpg","_t":5833,"_vc":100},{"_i":"ms_005867.jpg","_t":5867,"_vc":100}],[{"_i":"ms_000000.jpg","_t":0,"_vc":0},{"_i":"ms_001967.jpg","_t":1967,"_vc":14},{"_i":"ms_002000.jpg","_t":2000,"_vc":24},{"_i":"ms_002100.jpg","_t":2100,"_vc":29},{"_i":"ms_002234.jpg","_t":2234,"_vc":29},{"_i":"ms_002300.jpg","_t":2300,"_vc":57},{"_i":"ms_002334.jpg","_t":2334,"_vc":99},{"_i":"ms_002734.jpg","_t":2734,"_vc":99},{"_i":"ms_002800.jpg","_t":2800,"_vc":99},{"_i":"ms_002834.jpg","_t":2834,"_vc":99},{"_i":"ms_002867.jpg","_t":2867,"_vc":99},{"_i":"ms_002900.jpg","_t":2900,"_vc":99},{"_i":"ms_003200.jpg","_t":3200,"_vc":100},{"_i":"ms_003467.jpg","_t":3467,"_vc":100},{"_i":"ms_003800.jpg","_t":3800,"_vc":100},{"_i":"ms_003834.jpg","_t":3834,"_vc":100},{"_i":"ms_003900.jpg","_t":3900,"_vc":100}],[{"_i":"ms_000000.jpg","_t":0,"_vc":0},{"_i":"ms_002633.jpg","_t":2633,"_vc":99},{"_i":"ms_002700.jpg","_t":2700,"_vc":99},{"_i":"ms_002966.jpg","_t":2966,"_vc":99},{"_i":"ms_003200.jpg","_t":3200,"_vc":99},{"_i":"ms_003233.jpg","_t":3233,"_vc":100},{"_i":"ms_003766.jpg","_t":3766,"_vc":100},{"_i":"ms_003800.jpg","_t":3800,"_vc":100},{"_i":"ms_003833.jpg","_t":3833,"_vc":100}],[{"_i":"ms_000000.jpg","_t":0,"_vc":0},{"_i":"ms_002100.jpg","_t":2100,"_vc":24},{"_i":"ms_002334.jpg","_t":2334,"_vc":29},{"_i":"ms_002467.jpg","_t":2467,"_vc":99},{"_i":"ms_002500.jpg","_t":2500,"_vc":99},{"_i":"ms_002734.jpg","_t":2734,"_vc":99},{"_i":"ms_003234.jpg","_t":3234,"_vc":99},{"_i":"ms_003400.jpg","_t":3400,"_vc":100},{"_i":"ms_004034.jpg","_t":4034,"_vc":100},{"_i":"ms_004067.jpg","_t":4067,"_vc":100},{"_i":"ms_004134.jpg","_t":4134,"_vc":100}]],"visualComplete":[3700,3200,3233,3400],"lighthouse":[54,54,54,54],"pagespeed":[77,76,76,76]}}